mcp_chess/__init__.py
mcp_chess/__main__.py
mcp_chess/server.py
mcp_chess-0.1.9.dist-info/licenses/LICENSE
mcp_chess-0.1.9.dist-info/METADATA
mcp_chess-0.1.9.dist-info/WHEEL
mcp_chess-0.1.9.dist-info/entry_points.txt
mcp_chess-0.1.9.dist-info/top_level.txt
mcp_chess-0.1.9.dist-info/RECORD
