Metadata-Version: 2.4
Name: mcp-chess
Version: 0.1.9
Summary: MCP server for playing chess against AI
Requires-Python: >=3.11
License-File: LICENSE
Requires-Dist: mcp[cli]>=1.7.1
Requires-Dist: chess==1.9.4
Requires-Dist: uvicorn>=0.29.0
Requires-Dist: cairosvg>=2.5.1
Requires-Dist: Pillow>=10.0.0
Dynamic: license-file
